{
    "7": "Charm Person on contact 3/day",
    "15": "Clairaudience 90' 1 round 3/day",
    "22": "Clairvoyance 90' 1 round 3/day",
    "28": "Determine direction and depth 2/day",
    "34": "ESP 90' 1 round 3/day",
    "41": "Flying 120'/turn 1 hour/day",
    "47": "Heal 1/day",
    "54": "Illusion 360' 2/day",
    "61": "Levitation 1 turn 3/day",
    "67": "Strength 1/day",
    "75": "Telekinesis 250 lbs. 2/day",
    "81": "Telepathy 180' 2/day",
    "88": "Teleportation 600 pounds 1/day",
    "94": "X-ray vision 120' 2/day"
}
