{
    "Action": "Table",
    "Data": {
        "1": "Arrow (4d6)",
        "2": "Arrow (3d6)",
        "3": "Arrow (2d6)",
        "5": "Axe",
        "6": "Battle axe",
        "7": "Bolt (2d10)",
        "8": "Bolt (2d6)",
        "9": "Sling bullet (3d4)",
        "12": "Dagger",
        "13": "Dart (3d4)",
        "14": "Flail",
        "15": "Javelin (1d2)",
        "16": "Knife",
        "17": "Lance",
        "19": "Mace",
        "20": "Special",
        "21": "Pick",
        "22": "Morning star",
        "23": "Pole arm",
        "25": "Scimitar",
        "28": "Spear",
        "37": "Sword",
        "38": "Trident",
        "39": "Warhammer",
        "40": "Special"
    }
}
